automlapp/__init__.py
automlapp/app.py
automlapp/launcher.py
automlapp/logo.png
automlapp/requirements.txt
automlapp/runtool.bat
automlapp/modules/__init__.py
automlapp/modules/data_cleaning.py
automlapp/modules/data_input.py
automlapp/modules/data_preprocessing.py
automlapp/modules/data_summarization.py
automlapp/modules/data_visualization.py
automlapp/modules/data_woeiv.py
automlapp/modules/hyperparameter_tuning.py
automlapp/modules/model_evaluation.py
automlapp/modules/model_training.py
automlapp/modules/train_user_params.py
automlapp/modules/__pycache__/__init__.cpython-310.pyc
automlapp/modules/__pycache__/data_cleaning.cpython-310.pyc
automlapp/modules/__pycache__/data_input.cpython-310.pyc
automlapp/modules/__pycache__/data_preprocessing.cpython-310.pyc
automlapp/modules/__pycache__/data_summarization.cpython-310.pyc
automlapp/modules/__pycache__/data_visualization.cpython-310.pyc
automlapp/modules/__pycache__/data_woeiv.cpython-310.pyc
automlapp/modules/__pycache__/hyperparameter_tuning.cpython-310.pyc
automlapp/modules/__pycache__/model_evaluation.cpython-310.pyc
automlapp/modules/__pycache__/model_training.cpython-310.pyc
automlapp/modules/__pycache__/train_user_params.cpython-310.pyc
automlapp/utils/__init__.py
automlapp/utils/print_utils.py
automlapp/utils/streamlit_utils.py
automlapp/utils/__pycache__/__init__.cpython-310.pyc
automlapp/utils/__pycache__/print_utils.cpython-310.pyc
automlapp/utils/__pycache__/streamlit_utils.cpython-310.pyc
AutoMLApp-0.1.73.dist-info/LICENSE
AutoMLApp-0.1.73.dist-info/METADATA
AutoMLApp-0.1.73.dist-info/WHEEL
AutoMLApp-0.1.73.dist-info/entry_points.txt
AutoMLApp-0.1.73.dist-info/top_level.txt
AutoMLApp-0.1.73.dist-info/RECORD
