Metadata-Version: 2.1
Name: AutoMLApp
Version: 0.1.73
Summary: An automated machine learning application designed for efficient model training, evaluation, and hyperparameter tuning.
Author: Think360.ai
Author-email: shivam.nikam@think360.ai
Classifier: Programming Language :: Python :: 3
Classifier: License :: OSI Approved :: MIT License
Classifier: Operating System :: OS Independent
Requires-Python: >=3.10
License-File: LICENSE
